upstash_ratelimit/__init__.py
upstash_ratelimit/algorithm.py
upstash_ratelimit/config.py
upstash_ratelimit/limiter.py
upstash_ratelimit/py.typed
upstash_ratelimit/schema/response.py
upstash_ratelimit/utils/time.py
upstash_ratelimit_a-0.1.7.dist-info/LICENSE
upstash_ratelimit_a-0.1.7.dist-info/METADATA
upstash_ratelimit_a-0.1.7.dist-info/WHEEL
upstash_ratelimit_a-0.1.7.dist-info/RECORD
