Metadata-Version: 2.1
Name: upstash-ratelimit-a
Version: 0.1.7
Summary: 
Author: Zgîmbău Tudor
Author-email: tudor.zgimbau@gmail.com
Requires-Python: >=3.8,<4.0
Classifier: Programming Language :: Python :: 3
Classifier: Programming Language :: Python :: 3.8
Classifier: Programming Language :: Python :: 3.9
Classifier: Programming Language :: Python :: 3.10
Classifier: Programming Language :: Python :: 3.11
Requires-Dist: pytest (>=7.3.0,<8.0.0)
Requires-Dist: pytest-asyncio (>=0.21.0,<0.22.0)
Requires-Dist: upstash-redis-a (>=0.1.14,<0.2.0)
